[{"SN":"Iloni35","Age":20,"Gender":"Male","Item ID":93,"Item Name":"Apocalyptic Battlescythe","Price":4.49},{"SN":"Aidaira26","Age":21,"Gender":"Male","Item ID":12,"Item Name":"Dawne","Price":3.36},{"SN":"Irim47","Age":17,"Gender":"Male","Item ID":5,"Item Name":"Putrid Fan","Price":2.63},{"SN":"Irith83","Age":17,"Gender":"Male","Item ID":123,"Item Name":"Twilight's Carver","Price":2.55},{"SN":"Philodil43","Age":22,"Gender":"Male","Item ID":154,"Item Name":"Feral Katana","Price":4.11},{"SN":"Hainaria90","Age":8,"Gender":"Male","Item ID":8,"Item Name":"Purgatory, Gem of Regret","Price":2.22},{"SN":"Aerithllora36","Age":40,"Gender":"Male","Item ID":148,"Item Name":"Warmonger, Gift of Suffering's End","Price":4.65},{"SN":"Undirra90","Age":28,"Gender":"Male","Item ID":27,"Item Name":"Riddle, Tribute of Ended Dreams","Price":3.38},{"SN":"Eolideu96","Age":18,"Gender":"Male","Item ID":111,"Item Name":"Misery's End","Price":1.79},{"SN":"Aesurstilis64","Age":36,"Gender":"Male","Item ID":139,"Item Name":"Mercy, Katana of Dismay","Price":4.25},{"SN":"Jiskimsda56","Age":24,"Gender":"Male","Item ID":126,"Item Name":"Exiled Mithril Longsword","Price":1.08},{"SN":"Jiskim75","Age":36,"Gender":"Female","Item ID":173,"Item Name":"Stormfury Longsword","Price":4.01},{"SN":"Lirtassa77","Age":20,"Gender":"Female","Item ID":90,"Item Name":"Betrayer","Price":4.12},{"SN":"Hairith93","Age":32,"Gender":"Male","Item ID":23,"Item Name":"Crucifer","Price":1.62},{"SN":"Yarith71","Age":8,"Gender":"Male","Item ID":44,"Item Name":"Bonecarvin Battle Axe","Price":4.36},{"SN":"Sondim43","Age":23,"Gender":"Male","Item ID":94,"Item Name":"Mourning Blade","Price":3.64},{"SN":"Zhisrisu83","Age":24,"Gender":"Male","Item ID":174,"Item Name":"Primitive Blade","Price":1.36},{"SN":"Rarallo90","Age":9,"Gender":"Male","Item ID":156,"Item Name":"Soul-Forged Steel Shortsword","Price":4.53},{"SN":"Inadeu25","Age":12,"Gender":"Other \/ Non-Disclosed","Item ID":176,"Item Name":"Relentless Iron Skewer","Price":2.12},{"SN":"Haerithp41","Age":23,"Gender":"Male","Item ID":154,"Item Name":"Feral Katana","Price":4.11},{"SN":"Streural92","Age":35,"Gender":"Male","Item ID":10,"Item Name":"Sleepwalker","Price":1.81},{"SN":"Eoralphos86","Age":11,"Gender":"Male","Item ID":131,"Item Name":"Fury","Price":2.99},{"SN":"Shaidanu32","Age":16,"Gender":"Male","Item ID":172,"Item Name":"Blade of the Grave","Price":2.71},{"SN":"Lassimla92","Age":20,"Gender":"Male","Item ID":158,"Item Name":"Darkheart, Butcher of the Champion","Price":1.94},{"SN":"Heosurnuru52","Age":23,"Gender":"Male","Item ID":70,"Item Name":"Hope's End","Price":4.28},{"SN":"Ilara98","Age":17,"Gender":"Male","Item ID":71,"Item Name":"Demise","Price":3.09},{"SN":"Lirtistanya48","Age":7,"Gender":"Male","Item ID":98,"Item Name":"Deadline, Voice Of Subtlety","Price":1.29},{"SN":"Sundaky74","Age":25,"Gender":"Male","Item ID":117,"Item Name":"Heartstriker, Legacy of the Light","Price":4.71},{"SN":"Sondassasya91","Age":20,"Gender":"Female","Item ID":170,"Item Name":"Shadowsteel","Price":1.74},{"SN":"Arithllorin55","Age":21,"Gender":"Male","Item ID":90,"Item Name":"Betrayer","Price":4.12},{"SN":"Hairith93","Age":32,"Gender":"Male","Item ID":138,"Item Name":"Peacekeeper, Wit of Dark Magic","Price":2.63},{"SN":"Ethralan59","Age":33,"Gender":"Male","Item ID":129,"Item Name":"Fate, Vengeance of Eternal Justice","Price":2.88},{"SN":"Alarap40","Age":24,"Gender":"Female","Item ID":117,"Item Name":"Heartstriker, Legacy of the Light","Price":4.71},{"SN":"Pharithdil38","Age":16,"Gender":"Female","Item ID":0,"Item Name":"Splinter","Price":1.89},{"SN":"Chamjaskya75","Age":17,"Gender":"Male","Item ID":180,"Item Name":"Stormcaller","Price":2.77},{"SN":"Ila44","Age":20,"Gender":"Male","Item ID":104,"Item Name":"Gladiator's Glaive","Price":1.84},{"SN":"Airithrin43","Age":21,"Gender":"Female","Item ID":108,"Item Name":"Extraction, Quickblade Of Trembling Hands","Price":2.26},{"SN":"Chanjasksda31","Age":33,"Gender":"Male","Item ID":17,"Item Name":"Lazarus, Terror of the Earth","Price":1.96},{"SN":"Aiduecal76","Age":8,"Gender":"Male","Item ID":9,"Item Name":"Thorn, Conqueror of the Corrupted","Price":1.42},{"SN":"Heulaedru70","Age":21,"Gender":"Male","Item ID":155,"Item Name":"War-Forged Gold Deflector","Price":4.04},{"SN":"Eollym91","Age":20,"Gender":"Male","Item ID":18,"Item Name":"Torchlight, Bond of Storms","Price":3.75},{"SN":"Lirtastan49","Age":25,"Gender":"Male","Item ID":127,"Item Name":"Heartseeker, Reaver of Souls","Price":1.34},{"SN":"Undirrasta74","Age":20,"Gender":"Male","Item ID":64,"Item Name":"Fusion Pummel","Price":2.42},{"SN":"Chrathybust28","Age":21,"Gender":"Male","Item ID":16,"Item Name":"Restored Bauble","Price":2.15},{"SN":"Saralp86","Age":25,"Gender":"Male","Item ID":64,"Item Name":"Fusion Pummel","Price":2.42},{"SN":"Iskossaya95","Age":23,"Gender":"Male","Item ID":91,"Item Name":"Celeste","Price":2.92},{"SN":"Lisosiast26","Age":24,"Gender":"Male","Item ID":6,"Item Name":"Rusty Skull","Price":3.58},{"SN":"Eustyria89","Age":30,"Gender":"Male","Item ID":60,"Item Name":"Wolf","Price":2.7},{"SN":"Eusty71","Age":25,"Gender":"Male","Item ID":84,"Item Name":"Arcane Gem","Price":4.81},{"SN":"Frichilsa31","Age":20,"Gender":"Male","Item ID":14,"Item Name":"Possessed Core","Price":2.82},{"SN":"Filon68","Age":23,"Gender":"Male","Item ID":176,"Item Name":"Relentless Iron Skewer","Price":2.12},{"SN":"Palyon91","Age":28,"Gender":"Male","Item ID":1,"Item Name":"Crucifer","Price":3.67},{"SN":"Assistast50","Age":23,"Gender":"Female","Item ID":118,"Item Name":"Ghost Reaver, Longsword of Magic","Price":2.95},{"SN":"Seostylis96","Age":16,"Gender":"Female","Item ID":94,"Item Name":"Mourning Blade","Price":3.64},{"SN":"Iskadar31","Age":25,"Gender":"Male","Item ID":111,"Item Name":"Misery's End","Price":1.79},{"SN":"Pheodaisun84","Age":20,"Gender":"Male","Item ID":108,"Item Name":"Extraction, Quickblade Of Trembling Hands","Price":2.26},{"SN":"Yarmol79","Age":17,"Gender":"Male","Item ID":79,"Item Name":"Alpha, Oath of Zeal","Price":1.31},{"SN":"Aeri79","Age":23,"Gender":"Female","Item ID":107,"Item Name":"Splitter, Foe Of Subtlety","Price":4.15},{"SN":"Undosian34","Age":30,"Gender":"Female","Item ID":105,"Item Name":"Hailstorm Shadowsteel Scythe","Price":1.02},{"SN":"Aesririam61","Age":39,"Gender":"Female","Item ID":2,"Item Name":"Verdict","Price":2.65},{"SN":"Firon67","Age":23,"Gender":"Female","Item ID":68,"Item Name":"Storm-Weaver, Slayer of Inception","Price":4.39},{"SN":"Jiskjask76","Age":21,"Gender":"Male","Item ID":31,"Item Name":"Trickster","Price":4.59},{"SN":"Chanirra64","Age":18,"Gender":"Male","Item ID":25,"Item Name":"Hero Cane","Price":4.78},{"SN":"Isristira52","Age":11,"Gender":"Female","Item ID":41,"Item Name":"Orbit","Price":3.85},{"SN":"Chaniman66","Age":24,"Gender":"Male","Item ID":164,"Item Name":"Exiled Doomblade","Price":1.31},{"SN":"Yarithrgue83","Age":23,"Gender":"Male","Item ID":181,"Item Name":"Reaper's Toll","Price":4.12},{"SN":"Airi27","Age":24,"Gender":"Male","Item ID":4,"Item Name":"Bloodlord's Fetish","Price":1.91},{"SN":"Undilsan50","Age":22,"Gender":"Male","Item ID":94,"Item Name":"Mourning Blade","Price":3.64},{"SN":"Aidaira26","Age":21,"Gender":"Male","Item ID":82,"Item Name":"Nirvana","Price":1.77},{"SN":"Chamalo71","Age":34,"Gender":"Male","Item ID":126,"Item Name":"Exiled Mithril Longsword","Price":1.08},{"SN":"Undadar97","Age":25,"Gender":"Male","Item ID":98,"Item Name":"Deadline, Voice Of Subtlety","Price":1.29},{"SN":"Sundaky74","Age":25,"Gender":"Male","Item ID":60,"Item Name":"Wolf","Price":2.7},{"SN":"Lisirra44","Age":21,"Gender":"Male","Item ID":180,"Item Name":"Stormcaller","Price":2.77},{"SN":"Chamast86","Age":35,"Gender":"Male","Item ID":93,"Item Name":"Apocalyptic Battlescythe","Price":4.49},{"SN":"Ardcil81","Age":38,"Gender":"Male","Item ID":163,"Item Name":"Thunderfury Scimitar","Price":4.16},{"SN":"Heudai45","Age":15,"Gender":"Male","Item ID":167,"Item Name":"Malice, Legacy of the Queen","Price":3.25},{"SN":"Chaniman66","Age":24,"Gender":"Male","Item ID":97,"Item Name":"Swan Song, Gouger Of Terror","Price":1.92},{"SN":"Syalallodil59","Age":20,"Gender":"Male","Item ID":134,"Item Name":"Undead Crusader","Price":2.15}]